ms_teams_notify/__init__.py
ms_teams_notify/notify_to_teams.py
ms_teams_notify-0.1.5.dist-info/METADATA
ms_teams_notify-0.1.5.dist-info/WHEEL
ms_teams_notify-0.1.5.dist-info/top_level.txt
ms_teams_notify-0.1.5.dist-info/RECORD
