Metadata-Version: 2.1
Name: ms_teams_notify
Version: 0.1.5
Summary: Notify to Microsoft Teams with Adaptive Card.
Home-page: https://github.com/rue1-suzuki?tab=packages
Author: rue1-suzuki
Author-email: suzuki.ryuichi.1998@gmail.com
Classifier: Programming Language :: Python :: 3
Classifier: License :: OSI Approved :: MIT License
Classifier: Operating System :: OS Independent
Requires-Python: >=3.6
